[
    {
        "question": "Quem é o maior eng do brasil?",
        "choice1": "Renan",
        "choice2": "Diego",
        "choice3": "Peçanha",
        "choice4": "Noira",
        "answer": 1
    },
    {
        "question": "Quem é o eng mais bonito do brasil?",
        "choice1": "Renan",
        "choice2": "Diego",
        "choice3": "Peçanha",
        "choice4": "Noira",
        "answer": 1
    },
    {
        "question": "Quem é o mais feio do brasil?",
        "choice1": "Renan",
        "choice2": "Diego",
        "choice3": "Peçanha",
        "choice4": "Noira",
        "answer": 4
    }
]